InshortsApi/__init__.py
InshortsApi/inshorts.py
Inshorts_Api-0.0.1.dist-info/LICENSE
Inshorts_Api-0.0.1.dist-info/METADATA
Inshorts_Api-0.0.1.dist-info/WHEEL
Inshorts_Api-0.0.1.dist-info/top_level.txt
Inshorts_Api-0.0.1.dist-info/RECORD
