Metadata-Version: 2.1
Name: Inshorts-Api
Version: 0.0.1
Summary: UNKNOWN
Home-page: https://github.com/engineerscodes/Inshorts-Api
Author: M.NAVEEN
Author-email: practicalengineers05@gmail.com
License: MIT
Keywords: python,Inshorts,InshortsApi,Inshorts-Api
Platform: UNKNOWN
License-File: LICENSE
Requires-Dist: requests
Requires-Dist: bs4
Requires-Dist: lxml
Requires-Dist: html5lib
